ops/__init__.py
ops/git_utils.py
ops/main.py
ops/opsconfig.py
ops/simpleconsul.py
ops/simplessm.py
ops/simplevault.py
ops/ansible/__init__.py
ops/ansible/callback_plugins/__init__.py
ops/ansible/filter_plugins/__init__.py
ops/ansible/filter_plugins/commonfilters.py
ops/ansible/vars_plugins/__init__.py
ops/ansible/vars_plugins/clusterconfig.py
ops/ansible/vars_plugins/opsconfig.py
ops/cli/__init__.py
ops/cli/aws.py
ops/cli/config.py
ops/cli/config_generator.py
ops/cli/helmfile.py
ops/cli/inventory.py
ops/cli/packer.py
ops/cli/parser.py
ops/cli/playbook.py
ops/cli/run.py
ops/cli/ssh.py
ops/cli/sync.py
ops/cli/terraform.py
ops/data/ansible/ansible.cfg
ops/data/ansible/tasks/deploy_prometheus_alert_rules.yml
ops/data/ansible/tasks/install_rpm.yml
ops/data/ansible/tasks/remove_prometheus_alert_rules.yml
ops/data/ssh/ssh.config
ops/data/ssh/ssh.scb.proxy.config.tpl
ops/data/ssh/ssh.tunnel.config
ops/data/terraform/terraformrc
ops/hierarchical/__init__.py
ops/hierarchical/composition_config_generator.py
ops/inventory/SKMS.py
ops/inventory/__init__.py
ops/inventory/azurerm.py
ops/inventory/caching.py
ops/inventory/ec2inventory.py
ops/inventory/generator.py
ops/inventory/sshconfig.py
ops/inventory/plugin/__init__.py
ops/inventory/plugin/azr.py
ops/inventory/plugin/cns.py
ops/inventory/plugin/ec2.py
ops/inventory/plugin/legacy_pcs.py
ops/inventory/plugin/skms.py
ops/jinja/__init__.py
ops/terraform/__init__.py
ops/terraform/terraform_cmd_generator.py
ops_cli-2.3.2.dist-info/licenses/LICENSE
ops_cli-2.3.2.dist-info/METADATA
ops_cli-2.3.2.dist-info/WHEEL
ops_cli-2.3.2.dist-info/entry_points.txt
ops_cli-2.3.2.dist-info/top_level.txt
ops_cli-2.3.2.dist-info/RECORD
