Metadata-Version: 2.4
Name: ops-cli
Version: 2.3.2
Summary: Ops - wrapper for Terraform, Ansible, and SSH for cloud automation
Home-page: https://github.com/adobe/ops-cli
Author: Adobe
Author-email: noreply@adobe.com
License: Apache2
Classifier: Development Status :: 5 - Production/Stable
Classifier: Environment :: Web Environment
Classifier: Intended Audience :: Developers
Classifier: License :: OSI Approved :: Apache Software License
Classifier: Operating System :: OS Independent
Classifier: Programming Language :: Python :: 3
Classifier: Programming Language :: Python :: 3.9
Classifier: Programming Language :: Python :: 3.10
Classifier: Programming Language :: Python :: 3.11
Classifier: Programming Language :: Python :: Implementation :: CPython
Classifier: Programming Language :: Python :: Implementation :: PyPy
Classifier: Topic :: Internet :: WWW/HTTP :: Dynamic Content
Classifier: Topic :: Software Development :: Libraries :: Python Modules
Classifier: Topic :: Text Processing :: Markup :: HTML
Requires-Python: >=3.5
License-File: LICENSE
Requires-Dist: adal==1.2.7
Requires-Dist: ansible==8.7.0; python_version >= "3.9"
Requires-Dist: ansible-core==2.15.13; python_version >= "3.9"
Requires-Dist: awscli==1.42.30; python_version >= "3.9"
Requires-Dist: azure==4.0.0
Requires-Dist: azure-applicationinsights==0.1.1
Requires-Dist: azure-batch==4.1.3
Requires-Dist: azure-common==1.1.28
Requires-Dist: azure-core==1.36.0; python_version >= "3.9"
Requires-Dist: azure-cosmosdb-nspkg==2.0.2
Requires-Dist: azure-cosmosdb-table==1.0.6
Requires-Dist: azure-datalake-store==0.0.53
Requires-Dist: azure-eventgrid==1.3.0
Requires-Dist: azure-graphrbac==0.40.0
Requires-Dist: azure-keyvault==1.1.0
Requires-Dist: azure-loganalytics==0.1.1
Requires-Dist: azure-mgmt==4.0.0
Requires-Dist: azure-mgmt-advisor==1.0.1
Requires-Dist: azure-mgmt-applicationinsights==0.1.1
Requires-Dist: azure-mgmt-authorization==0.50.0
Requires-Dist: azure-mgmt-batch==5.0.1
Requires-Dist: azure-mgmt-batchai==2.0.0
Requires-Dist: azure-mgmt-billing==0.2.0
Requires-Dist: azure-mgmt-cdn==3.1.0
Requires-Dist: azure-mgmt-cognitiveservices==3.0.0
Requires-Dist: azure-mgmt-commerce==1.0.1
Requires-Dist: azure-mgmt-compute==4.6.2
Requires-Dist: azure-mgmt-consumption==2.0.0
Requires-Dist: azure-mgmt-containerinstance==1.5.0
Requires-Dist: azure-mgmt-containerregistry==2.8.0
Requires-Dist: azure-mgmt-containerservice==4.4.0
Requires-Dist: azure-mgmt-cosmosdb==0.4.1
Requires-Dist: azure-mgmt-datafactory==0.6.0
Requires-Dist: azure-mgmt-datalake-analytics==0.6.0
Requires-Dist: azure-mgmt-datalake-nspkg==3.0.1
Requires-Dist: azure-mgmt-datalake-store==0.5.0
Requires-Dist: azure-mgmt-datamigration==1.0.0
Requires-Dist: azure-mgmt-devspaces==0.1.0
Requires-Dist: azure-mgmt-devtestlabs==2.2.0
Requires-Dist: azure-mgmt-dns==2.1.0
Requires-Dist: azure-mgmt-eventgrid==1.0.0
Requires-Dist: azure-mgmt-eventhub==2.6.0
Requires-Dist: azure-mgmt-hanaonazure==0.1.1
Requires-Dist: azure-mgmt-iotcentral==0.1.0
Requires-Dist: azure-mgmt-iothub==0.5.0
Requires-Dist: azure-mgmt-iothubprovisioningservices==0.2.0
Requires-Dist: azure-mgmt-keyvault==1.1.0
Requires-Dist: azure-mgmt-loganalytics==0.2.0
Requires-Dist: azure-mgmt-logic==3.0.0
Requires-Dist: azure-mgmt-machinelearningcompute==0.4.1
Requires-Dist: azure-mgmt-managementgroups==0.1.0
Requires-Dist: azure-mgmt-managementpartner==0.1.1
Requires-Dist: azure-mgmt-maps==0.1.0
Requires-Dist: azure-mgmt-marketplaceordering==0.1.0
Requires-Dist: azure-mgmt-media==1.0.1
Requires-Dist: azure-mgmt-monitor==0.5.2
Requires-Dist: azure-mgmt-msi==0.2.0
Requires-Dist: azure-mgmt-network==2.7.0
Requires-Dist: azure-mgmt-notificationhubs==2.1.0
Requires-Dist: azure-mgmt-nspkg==3.0.2
Requires-Dist: azure-mgmt-policyinsights==0.1.0
Requires-Dist: azure-mgmt-powerbiembedded==2.0.0
Requires-Dist: azure-mgmt-rdbms==1.9.0
Requires-Dist: azure-mgmt-recoveryservices==0.3.0
Requires-Dist: azure-mgmt-recoveryservicesbackup==0.3.0
Requires-Dist: azure-mgmt-redis==5.0.0
Requires-Dist: azure-mgmt-relay==0.1.0
Requires-Dist: azure-mgmt-reservations==0.2.1
Requires-Dist: azure-mgmt-resource==2.2.0
Requires-Dist: azure-mgmt-scheduler==2.0.0
Requires-Dist: azure-mgmt-search==2.1.0
Requires-Dist: azure-mgmt-servicebus==0.5.3
Requires-Dist: azure-mgmt-servicefabric==0.2.0
Requires-Dist: azure-mgmt-signalr==0.1.1
Requires-Dist: azure-mgmt-sql==0.9.1
Requires-Dist: azure-mgmt-storage==2.0.0
Requires-Dist: azure-mgmt-subscription==0.2.0
Requires-Dist: azure-mgmt-trafficmanager==0.50.0
Requires-Dist: azure-mgmt-web==0.35.0
Requires-Dist: azure-nspkg==3.0.2
Requires-Dist: azure-servicebus==0.21.1
Requires-Dist: azure-servicefabric==6.3.0.0
Requires-Dist: azure-servicemanagement-legacy==0.20.8
Requires-Dist: azure-storage-blob==1.5.0
Requires-Dist: azure-storage-common==1.4.2
Requires-Dist: azure-storage-file==1.4.0
Requires-Dist: azure-storage-queue==1.4.0
Requires-Dist: boto3==1.40.30; python_version >= "3.9"
Requires-Dist: botocore==1.40.30; python_version >= "3.9"
Requires-Dist: cachetools==6.2.1; python_version >= "3.9"
Requires-Dist: certifi==2025.11.12; python_version >= "3.7"
Requires-Dist: cffi==2.0.0; python_version >= "3.9"
Requires-Dist: charset-normalizer==3.4.4; python_version >= "3.7"
Requires-Dist: colorama==0.4.6; python_version >= "2.7" and python_version not in "3.0, 3.1, 3.2, 3.3, 3.4, 3.5, 3.6"
Requires-Dist: cryptography==46.0.3; python_version >= "3.8" and python_full_version not in "3.9.0, 3.9.1"
Requires-Dist: deepmerge==2.0; python_version >= "3.8"
Requires-Dist: docutils==0.19; python_version >= "3.7"
Requires-Dist: durationpy==0.10
Requires-Dist: gitdb==4.0.12; python_version >= "3.7"
Requires-Dist: gitpython==3.1.45; python_version >= "3.7"
Requires-Dist: google-auth==2.43.0; python_version >= "3.7"
Requires-Dist: hashmerge==0.2
Requires-Dist: himl==0.18.0; python_version >= "3.9"
Requires-Dist: hvac==1.2.1; python_full_version >= "3.6.2" and python_full_version < "4.0.0"
Requires-Dist: idna==3.11; python_version >= "3.8"
Requires-Dist: inflection==0.5.1; python_version >= "3.5"
Requires-Dist: isodate==0.7.2; python_version >= "3.7"
Requires-Dist: jinja2==3.1.6; python_version >= "3.7"
Requires-Dist: jmespath==1.0.1; python_version >= "3.7"
Requires-Dist: kubernetes==33.1.0; python_version >= "3.6"
Requires-Dist: markupsafe==3.0.3; python_version >= "3.9"
Requires-Dist: msal==1.34.0; python_version >= "3.8"
Requires-Dist: msrest==0.7.1; python_version >= "3.6"
Requires-Dist: msrestazure==0.6.4
Requires-Dist: oauthlib==3.3.1; python_version >= "3.8"
Requires-Dist: packaging==25.0; python_version >= "3.8"
Requires-Dist: passgen==1.1.1
Requires-Dist: pathlib2==2.3.7.post1
Requires-Dist: pyasn1==0.6.1; python_version >= "3.8"
Requires-Dist: pyasn1-modules==0.4.2; python_version >= "3.8"
Requires-Dist: pycparser==2.23; python_version >= "3.8"
Requires-Dist: pyhcl==0.4.5
Requires-Dist: pyjwt[crypto]==2.10.1; python_version >= "3.9"
Requires-Dist: python-consul==1.1.0
Requires-Dist: python-dateutil==2.9.0.post0; python_version >= "2.7" and python_version not in "3.0, 3.1, 3.2"
Requires-Dist: pyyaml==6.0.1; python_version >= "3.6"
Requires-Dist: requests==2.32.5; python_version >= "3.9"
Requires-Dist: requests-oauthlib==2.0.0; python_version >= "3.4"
Requires-Dist: resolvelib==1.0.1
Requires-Dist: rsa==4.7.2; python_version >= "3.5" and python_version < "4"
Requires-Dist: s3transfer==0.14.0; python_version >= "3.9"
Requires-Dist: simpledi==0.4.1
Requires-Dist: six==1.17.0; python_version >= "2.7" and python_version not in "3.0, 3.1, 3.2"
Requires-Dist: smmap==5.0.2; python_version >= "3.7"
Requires-Dist: typing-extensions==4.15.0; python_version >= "3.9"
Requires-Dist: urllib3==2.5.0; python_version >= "3.9"
Requires-Dist: websocket-client==1.9.0; python_version >= "3.9"
Dynamic: author
Dynamic: author-email
Dynamic: classifier
Dynamic: description
Dynamic: description-content-type
Dynamic: home-page
Dynamic: license
Dynamic: license-file
Dynamic: requires-dist
Dynamic: requires-python
Dynamic: summary
